Kara/__init__.py
Kara/kara.py
Kara/util.py
Kara/Core/compiler.py
Kara/Core/core.py
Kara/Core/Abilities/Kara_Games/config.json
Kara/Core/Abilities/Kara_Games/main.py
Kara/Core/Abilities/Kara_General/config.json
Kara/Core/Abilities/Kara_General/main.py
Kara/Core/Abilities/Kara_Maths/config.json
Kara/Core/Abilities/Kara_Maths/main.py
Kara/Core/Abilities/Kara_Time/config.json
Kara/Core/Abilities/Kara_Time/main.py
Kara/Core/Abilities/Kara_Weather/config.json
Kara/Core/Abilities/Kara_Weather/main.py
Kara/Core/Abilities/Kara_Weather/requirements.txt
Kara/Core/Abilities/Kara_Weather/weather.py
Kara/Core/Data/boot.txt
Kara/Core/Data/usage.txt
Kara/Core/Data/Cache/abilities.json
Kara/Core/Data/Cache/commands.json
Kara/Core/Data/Cache/fallback.txt
Kara/Core/Data/Cache/last.txt
Kara/Core/Data/Cache/link.py
Kara/Core/Data/Docs/CHANGELOG.md
Kara/Core/Data/Docs/abilities.md
Kara/Core/Data/Docs/commands.md
Kara/Core/Data/Docs/integrations.md
Kara/Core/Data/Docs/sneakpeak.md
Kara/Core/Data/Docs/sneakpeak.txt
Kara/Core/Data/Templates/Ability/config.json
Kara/Core/Data/Templates/Ability/main.py
Kara/Core/Data/Templates/Ability/requirements.txt
Kara/Core/Data/Templates/Integration/main.py
Kara/Core/Scripts/colors.py
Kara/Core/Scripts/handler.py
Kara/Core/Scripts/setup.py
Kara-1.2.2b0.dist-info/LICENSE
Kara-1.2.2b0.dist-info/METADATA
Kara-1.2.2b0.dist-info/WHEEL
Kara-1.2.2b0.dist-info/entry_points.txt
Kara-1.2.2b0.dist-info/top_level.txt
Kara-1.2.2b0.dist-info/RECORD
