Metadata-Version: 2.1
Name: Kara
Version: 1.2.2b0
Summary: Modular and Fully Customizable Virtual Assistant
Home-page: https://github.com/emileclarkb/Kara
Author: Emile Clark-Boman
Author-email: eclarkboman@gmail.com
License: GPLv3
Keywords: voice,alexa,siri,cortana,google,assistant,customize,recognition,assistant,control,commands,artificial,intelligence
Platform: UNKNOWN
Classifier: Development Status :: 4 - Beta
Classifier: License :: OSI Approved :: GNU General Public License v3 (GPLv3)
Classifier: Programming Language :: Python :: 3
Classifier: Programming Language :: Python :: 3.8
Classifier: Operating System :: OS Independent
Requires-Python: >=3.0
Requires-Dist: SpeechRecognition
Requires-Dist: pyttsx3
Requires-Dist: pyaudio
Requires-Dist: wheel
Requires-Dist: pathlib
Requires-Dist: termcolor
Requires-Dist: colorama
Requires-Dist: ffmpeg
